{
    "DS": [
        {
            "executionStatus": "success",
            "dataset": "ds.xpt",
            "domain": "DS",
            "variables": [],
            "message": null,
            "errors": []
        }
    ],
    "DM": [
        {
            "executionStatus": "skipped",
            "dataset": "dm.xpt",
            "domain": "DM",
            "variables": [],
            "message": "Rule skipped - doesn't apply to domain for rule id=None, dataset=DM",
            "errors": []
        }
    ]
}