{
  "datasets": [
    {
      "dataset": "ts.xpt",
      "domain": "TS",
      "execution_status": "success",
      "execution_message": "The set  ('INTMODEL\u2019, 'INTTYPE','PCLASS') is not in the list of TSPARAMCD with TSVAL populated.",
      "number_errors": 2,
      "errors": [
        {
          "row": 2,
          "SEQ": 1,
          "USUBJID": "None",
          "value": {
            "$STYPE_INTERVENTIONAL": 1,
            "TSPARMCD": "INTTYPE",
            "TSVAL": null
          },
          "validated": false
        },
        {
          "row": 3,
          "SEQ": 1,
          "USUBJID": "None",
          "value": {
            "$STYPE_INTERVENTIONAL": 1,
            "TSPARMCD": "PCLASS",
            "TSVAL": null
          },
          "validated": false
        }
      ]
    }
  ],
  "unvalidated_highlights": [
    {
      "Sheet": "ts.xpt",
      "Row": 5,
      "Variable": "TSPARMCD"
    },
    {
      "Sheet": "ts.xpt",
      "Row": 5,
      "Variable": "TSVAL"
    },
    {
      "Sheet": "ts.xpt",
      "Row": 6,
      "Variable": "TSPARMCD"
    },
    {
      "Sheet": "ts.xpt",
      "Row": 6,
      "Variable": "TSVAL"
    },
    {
      "Sheet": "ts.xpt",
      "Row": 7,
      "Variable": "TSPARMCD"
    },
    {
      "Sheet": "ts.xpt",
      "Row": 8,
      "Variable": "TSPARMCD"
    },
    {
      "Sheet": "ts.xpt",
      "Row": 8,
      "Variable": "TSVAL"
    }
  ]
}