{
  "datasets": [
    {
      "dataset": "ds.xpt",
      "domain": "DS",
      "execution_status": "success",
      "execution_message": "More than one record per subject per DSSCAT per EPOCH",
      "number_errors": 2,
      "errors": [
        {
          "row": 5,
          "SEQ": 2,
          "USUBJID": "CDISC002",
          "value": {
            "DSSCAT": "STUDY PARTICIPATION",
            "EPOCH": "TREATMENT"
          },
          "highlighted_in_test_case": false
        },
        {
          "row": 6,
          "SEQ": 3,
          "USUBJID": "CDISC002",
          "value": {
            "DSSCAT": "STUDY PARTICIPATION",
            "EPOCH": "TREATMENT"
          },
          "highlighted_in_test_case": false
        }
      ]
    }
  ]
}