{
  "datasets": [
    {
      "dataset": "vs.xpt",
      "domain": "VS",
      "execution_status": "success",
      "execution_message": "Record has a last observation before exposure flag (VSLOBXFL = 'Y') but character standard result (VSSTRESC) is missing.",
      "number_errors": 1,
      "errors": [
        {
          "row": 3,
          "SEQ": 3,
          "USUBJID": "CDISC001",
          "value": {
            "VSLOBXFL": "Y",
            "VSTESTCD": "DIABP",
            "VSSTRESC": null
          },
          "validated": true
        }
      ]
    }
  ]
}