{
  "TS": [
    {
      "executionStatus": "skipped",
      "dataset": "ts.xpt",
      "domain": "TS",
      "variables": [],
      "message": "Rule skipped - doesn't apply to domain for rule id=None, dataset=TS",
      "errors": []
    }
  ],
  "DM": [
    {
      "executionStatus": "success",
      "dataset": "dm.xpt",
      "domain": "DM",
      "variables": [
        "ARMNRS"
      ],
      "message": "A subject has a record in EX but is not assigned to a treatment while participating in an interventional study",
      "errors": [
        {
          "value": {
            "ARMNRS": "SCREEN FAILURE"
          },
          "dataset": "dm.xpt",
          "row": 1,
          "USUBJID": "ABC123"
        },
        {
          "value": {
            "ARMNRS": "ASSIGNED, NOT TREATED"
          },
          "dataset": "dm.xpt",
          "row": 3,
          "USUBJID": "ZZZ100"
        }
      ]
    }
  ],
  "EX": [
    {
      "executionStatus": "skipped",
      "dataset": "ex.xpt",
      "domain": "EX",
      "variables": [],
      "message": "Rule skipped - doesn't apply to domain for rule id=None, dataset=EX",
      "errors": []
    }
  ]
}