{
  "datasets": [
    {
      "dataset": "co.xpt",
      "domain": "CO",
      "execution_status": "success",
      "execution_message": "RDOMAIN has a missing value when IDVARVAL has a non-missing value.",
      "number_errors": 2,
      "errors": [
        {
          "row": 3,
          "SEQ": 3,
          "USUBJID": "YY-20",
          "value": {
            "IDVAR": "AESEQ",
            "IDVARVAL": "7",
            "RDOMAIN": null
          },
          "highlighted_in_test_case": false
        },
        {
          "row": 5,
          "SEQ": 5,
          "USUBJID": "AB-99",
          "value": {
            "IDVAR": "VSGRPID",
            "IDVARVAL": "VS2",
            "RDOMAIN": null
          },
          "highlighted_in_test_case": false
        }
      ]
    }
  ]
}